pip_rewind/cli.py
pip_rewind/parser.py
pip_rewind/versions.py
pip_rewind-0.1.1.dist-info/entry_points.txt
pip_rewind-0.1.1.dist-info/LICENSE
pip_rewind-0.1.1.dist-info/WHEEL
pip_rewind-0.1.1.dist-info/METADATA
pip_rewind-0.1.1.dist-info/RECORD
