Metadata-Version: 2.1
Name: pip-rewind
Version: 0.1.1
Summary: Install python modules from pypi from a previous date in history
Home-page: https://github.com/Amar1729/pip-rewind
License: MIT
Keywords: packaging,dependency
Author: Amar Paul
Author-email: amar.paul16@gmail.com
Requires-Python: >=3.7,<4.0
Classifier: Environment :: Console
Classifier: Intended Audience :: Developers
Classifier: License :: OSI Approved :: MIT License
Classifier: Programming Language :: Python :: 3
Classifier: Programming Language :: Python :: 3.7
Classifier: Programming Language :: Python :: 3.8
Classifier: Programming Language :: Python :: 3.9
Classifier: Topic :: Software Development :: Build Tools
Requires-Dist: python-dateutil (>=2.8.1,<3.0.0)
Requires-Dist: pytz (>=2021.1,<2022.0)
Requires-Dist: result (>=0.6.0,<0.7.0)
Requires-Dist: rss-parser (>=0.2.3,<0.3.0)
Requires-Dist: tzlocal (>=2.1,<3.0)
Project-URL: Repository, https://github.com/Amar1729/pip-rewind
